regexfactory/__init__.py
regexfactory/chars.py
regexfactory/pattern.py
regexfactory/patterns.py
RegexFactory-1.0.1.dist-info/LICENSE
RegexFactory-1.0.1.dist-info/METADATA
RegexFactory-1.0.1.dist-info/WHEEL
RegexFactory-1.0.1.dist-info/top_level.txt
RegexFactory-1.0.1.dist-info/zip-safe
RegexFactory-1.0.1.dist-info/RECORD
