Metadata-Version: 2.1
Name: RegexFactory
Version: 1.0.1
Author: GrandMoff100
Author-email: nlarsen23.student@gmail.com
License: GPLv3
Keywords: regex,generator,regular expression,strings
Classifier: License :: OSI Approved :: GNU General Public License v3 (GPLv3)
Classifier: Programming Language :: Python :: 3
Classifier: Operating System :: OS Independent
Classifier: Programming Language :: Python
Classifier: Development Status :: 4 - Beta
Classifier: Intended Audience :: Developers
Classifier: Topic :: Software Development :: Libraries
License-File: LICENSE
Provides-Extra: dev
Requires-Dist: isort ; extra == 'dev'
Requires-Dist: black ; extra == 'dev'
Requires-Dist: flake8 ; extra == 'dev'
Requires-Dist: pylint ; extra == 'dev'
Requires-Dist: pytest ; extra == 'dev'
Requires-Dist: hypothesis ; extra == 'dev'
